{
  "father": {
    "type": "laser",
    "cnName": "激光枪",
    "bullet": {
      "name": "laser1",
      "cnName": "激光枪",
      "randomPro": 1,
      "iconUrl": "laser/icon",
      "capacity": "6,12",
      "attackGap": "0.30,0.50",
      "reloadGap": "1.5,2.5",
      "shakeAngle": 0,
      "bulletWidth": "600,950",
      "bulletNum": 1,
      "beatBack": 2,
      "targetShakeValue": 3,
      "hurtRatio": 4,
      "gunNum": 1,
      "armsArmMul": 0.5,
      "armsWeight": 5,
      "upValue": 3,
      "shootShakeAngle": 25,
      "shootRecoil": 4,
      "bulletLife": 0.1,
      "hitType": "longLine",
      "dpsMul": 0.9,
      "uiDpsMul": 2.1,
      "shootSoundUrl": null,
      "flipX": 1,
      "fireImgUrl": {
        "name": "blueLaserShoot"
      },
      "bulletImgUrl": {
        "value": "bullet/blueLaser",
        "raNum": 60,
        "con": "add",
        "len": 20,
        "everFleshB": true,
        "imgDieType": "die",
        "time": -1,
        "bottomLayerB": true
      },
      "hitImgUrl": {
        "name": "blueLaserShoot"
      },
      "allImgRange": "laser",
      "bodyImgRange": "laser/body2",
      "barrelImgRange": "laser/barrel2,laser/barrel3",
      "stockImgRange": "laser/stock2",
      "gripImgRange": "laser/grip2",
      "glassImgRange": "laser/glass,laser/glass2"
    }
  }
}